quackinter/__init__.py
quackinter/commands/__init__.py
quackinter/commands/altchar.py
quackinter/commands/altstring.py
quackinter/commands/command.py
quackinter/commands/default_delay.py
quackinter/commands/default_string_delay.py
quackinter/commands/delay.py
quackinter/commands/general_key.py
quackinter/commands/hold_release.py
quackinter/commands/media.py
quackinter/commands/println.py
quackinter/commands/rem.py
quackinter/commands/repeat.py
quackinter/commands/string.py
quackinter/commands/string_delay.py
quackinter/commands/stringln.py
quackinter/commands/sysrq.py
quackinter/commands/wait_for_button_press.py
quackinter/config.py
quackinter/environment.py
quackinter/errors.py
quackinter/interpreter.py
quackinter/key_injector.py
quackinter/line.py
quackinter/quackinter.py
quackinter/sanitizer.py
quackinter/stack.py
quackinter/stack_context.py
quackinter/stack_trace.py
quackinter/utils.py
quackinter-0.2.3.dist-info/METADATA
quackinter-0.2.3.dist-info/WHEEL
quackinter-0.2.3.dist-info/RECORD
