Metadata-Version: 2.3
Name: quackinter
Version: 0.2.3
Summary: A sophisticated interpreter for DuckyScript 1.0 and flipper specific commands.
Keywords: duckyscript,flipper,ducky,key injection
Author: Dragon of Shuu
Author-email: 68718280+DragonOfShuu@users.noreply.github.com
Requires-Python: >=3.11,<4.0
Classifier: Programming Language :: Python :: 3
Classifier: Programming Language :: Python :: 3.11
Classifier: Programming Language :: Python :: 3.12
Classifier: Programming Language :: Python :: 3.13
Requires-Dist: pyautogui (>=0.9.54,<0.10.0)
Requires-Dist: screen-brightness-control (>=0.24.0,<0.25.0)
Project-URL: Documentation, https://ducklingscript.dragonofshuu.dev/
Project-URL: Repository, https://github.com/DragonOfShuu/quackinter
